CHANGELOG.rst
MANIFEST.in
README.rst
setup.py
eventlite/__init__.py
eventlite.egg-info/PKG-INFO
eventlite.egg-info/SOURCES.txt
eventlite.egg-info/dependency_links.txt
eventlite.egg-info/not-zip-safe
eventlite.egg-info/pbr.json
eventlite.egg-info/top_level.txt
eventlite/utils/__init__.py
eventlite/utils/local.py