Metadata-Version: 1.1
Name: eventlite
Version: 0.1.1
Summary: UNKNOWN
Home-page: PACKAGE_URL
Author: Samuele Santi
Author-email: UNKNOWN
License: BSD License
Platform: UNKNOWN
Classifier: License :: OSI Approved :: BSD License
Classifier: Development Status :: 5 - Production/Stable
Classifier: Programming Language :: Python :: 2.7
Classifier: Programming Language :: Python :: 3.4
